<world.GDXWorld>
  <levels>
    <world.GDXLevel>
      <name>Plains</name>
      <coordinates>
        <x>0.0</x>
        <y>0.0</y>
      </coordinates>
      <tiles/>
      <circles/>
      <polygons>
        <world.shape.GDXPolygon>
          <name>Polygon-0</name>
          <resource>dirt1.png</resource>
          <density>1.0</density>
          <friction>0.8</friction>
          <restitution>0.3</restitution>
          <bodyType>StaticBody</bodyType>
          <center>
            <x>7.707495</x>
            <y>-17.993446</y>
          </center>
          <filter>
            <categoryBits>1</categoryBits>
            <maskBits>-1</maskBits>
            <groupIndex>0</groupIndex>
          </filter>
          <repeatable>true</repeatable>
          <vertices>
            <Vector2>
              <x>-12.345701</x>
              <y>17.331198</y>
            </Vector2>
            <Vector2>
              <x>13.726479</x>
              <y>17.312574</y>
            </Vector2>
            <Vector2>
              <x>15.332941</x>
              <y>17.557049</y>
            </Vector2>
            <Vector2>
              <x>16.75677</x>
              <y>18.006828</y>
            </Vector2>
            <Vector2>
              <x>18.117315</x>
              <y>18.494087</y>
            </Vector2>
            <Vector2>
              <x>20.468847</x>
              <y>-78.5587</y>
            </Vector2>
            <Vector2>
              <x>-35.601765</x>
              <y>-76.59818</y>
            </Vector2>
            <Vector2>
              <x>-36.454884</x>
              <y>66.45515</y>
            </Vector2>
          </vertices>
        </world.shape.GDXPolygon>
        <world.shape.GDXPolygon>
          <name>Polygon-3</name>
          <resource>dirt1.png</resource>
          <density>1.0</density>
          <friction>0.5</friction>
          <restitution>0.3</restitution>
          <bodyType>StaticBody</bodyType>
          <center>
            <x>91.85733</x>
            <y>-10.63511</y>
          </center>
          <filter>
            <categoryBits>1</categoryBits>
            <maskBits>-1</maskBits>
            <groupIndex>0</groupIndex>
          </filter>
          <repeatable>true</repeatable>
          <vertices>
            <Vector2>
              <x>-66.04043</x>
              <y>11.119938</y>
            </Vector2>
            <Vector2>
              <x>-64.81238</x>
              <y>11.415105</y>
            </Vector2>
            <Vector2>
              <x>-63.15718</x>
              <y>11.531063</y>
            </Vector2>
            <Vector2>
              <x>-61.323997</x>
              <y>11.288605</y>
            </Vector2>
            <Vector2>
              <x>-58.645428</x>
              <y>10.339854</y>
            </Vector2>
            <Vector2>
              <x>-55.652096</x>
              <y>8.965897</y>
            </Vector2>
            <Vector2>
              <x>-51.775772</x>
              <y>8.490361</y>
            </Vector2>
            <Vector2>
              <x>-47.849262</x>
              <y>8.609245</y>
            </Vector2>
            <Vector2>
              <x>-45.076874</x>
              <y>8.921316</y>
            </Vector2>
            <Vector2>
              <x>-42.40533</x>
              <y>9.513044</y>
            </Vector2>
            <Vector2>
              <x>-40.69824</x>
              <y>10.23236</y>
            </Vector2>
            <Vector2>
              <x>-38.303722</x>
              <y>11.033107</y>
            </Vector2>
            <Vector2>
              <x>-34.866615</x>
              <y>11.508126</y>
            </Vector2>
            <Vector2>
              <x>-32.575214</x>
              <y>11.168825</y>
            </Vector2>
            <Vector2>
              <x>-29.722416</x>
              <y>10.300219</y>
            </Vector2>
            <Vector2>
              <x>-27.820557</x>
              <y>9.228032</y>
            </Vector2>
            <Vector2>
              <x>-26.247215</x>
              <y>8.029686</y>
            </Vector2>
            <Vector2>
              <x>-24.933647</x>
              <y>7.4276004</y>
            </Vector2>
            <Vector2>
              <x>-20.866028</x>
              <y>6.5772758</y>
            </Vector2>
            <Vector2>
              <x>-16.319862</x>
              <y>6.5772758</y>
            </Vector2>
            <Vector2>
              <x>-12.551323</x>
              <y>8.136206</y>
            </Vector2>
            <Vector2>
              <x>-9.85952</x>
              <y>9.765991</y>
            </Vector2>
            <Vector2>
              <x>-7.8257065</x>
              <y>11.04148</y>
            </Vector2>
            <Vector2>
              <x>-4.0571747</x>
              <y>12.246105</y>
            </Vector2>
            <Vector2>
              <x>-1.3653641</x>
              <y>11.962666</y>
            </Vector2>
            <Vector2>
              <x>1.804985</x>
              <y>10.828898</y>
            </Vector2>
            <Vector2>
              <x>3.539711</x>
              <y>9.411692</y>
            </Vector2>
            <Vector2>
              <x>5.5735245</x>
              <y>7.002438</y>
            </Vector2>
            <Vector2>
              <x>7.2484283</x>
              <y>5.5143704</y>
            </Vector2>
            <Vector2>
              <x>8.444794</x>
              <y>4.5931845</y>
            </Vector2>
            <Vector2>
              <x>10.598244</x>
              <y>3.2468362</y>
            </Vector2>
            <Vector2>
              <x>14.7855</x>
              <y>0.9793043</y>
            </Vector2>
            <Vector2>
              <x>18.853119</x>
              <y>-0.72134495</y>
            </Vector2>
            <Vector2>
              <x>23.459106</x>
              <y>-1.7842512</y>
            </Vector2>
            <Vector2>
              <x>29.73999</x>
              <y>-1.0756464</y>
            </Vector2>
            <Vector2>
              <x>32.730896</x>
              <y>1.3336058</y>
            </Vector2>
            <Vector2>
              <x>37.21724</x>
              <y>5.5143685</y>
            </Vector2>
            <Vector2>
              <x>39.49031</x>
              <y>7.8527603</y>
            </Vector2>
            <Vector2>
              <x>42.89995</x>
              <y>10.049431</y>
            </Vector2>
            <Vector2>
              <x>46.668472</x>
              <y>11.041478</y>
            </Vector2>
            <Vector2>
              <x>50.257553</x>
              <y>9.765988</y>
            </Vector2>
            <Vector2>
              <x>53.00917</x>
              <y>7.0732965</y>
            </Vector2>
            <Vector2>
              <x>55.820602</x>
              <y>3.601138</y>
            </Vector2>
            <Vector2>
              <x>57.674973</x>
              <y>0.9793043</y>
            </Vector2>
            <Vector2>
              <x>60.247147</x>
              <y>-1.5008097</y>
            </Vector2>
            <Vector2>
              <x>75.70445</x>
              <y>-8.560826</y>
            </Vector2>
            <Vector2>
              <x>82.1302</x>
              <y>-9.391223</y>
            </Vector2>
            <Vector2>
              <x>95.44905</x>
              <y>-9.529622</y>
            </Vector2>
            <Vector2>
              <x>98.98836</x>
              <y>-152.85715</y>
            </Vector2>
            <Vector2>
              <x>-67.58403</x>
              <y>-158.79659</y>
            </Vector2>
          </vertices>
        </world.shape.GDXPolygon>
        <world.shape.GDXPolygon>
          <name>Polygon-59</name>
          <resource>dirt1.png</resource>
          <density>1.0</density>
          <friction>0.5</friction>
          <restitution>0.3</restitution>
          <bodyType>StaticBody</bodyType>
          <center>
            <x>185.1065</x>
            <y>-19.371418</y>
          </center>
          <filter>
            <categoryBits>1</categoryBits>
            <maskBits>-1</maskBits>
            <groupIndex>0</groupIndex>
          </filter>
          <repeatable>true</repeatable>
          <vertices>
            <Vector2>
              <x>-4.87265</x>
              <y>-0.7683716</y>
            </Vector2>
            <Vector2>
              <x>-2.388855</x>
              <y>-0.65592575</y>
            </Vector2>
            <Vector2>
              <x>-0.8226471</x>
              <y>-0.4872589</y>
            </Vector2>
            <Vector2>
              <x>0.5695343</x>
              <y>-0.074962616</y>
            </Vector2>
            <Vector2>
              <x>1.265625</x>
              <y>0.3935547</y>
            </Vector2>
            <Vector2>
              <x>1.9300842</x>
              <y>0.99325943</y>
            </Vector2>
            <Vector2>
              <x>2.119934</x>
              <y>1.3680744</y>
            </Vector2>
            <Vector2>
              <x>2.1990356</x>
              <y>-0.7683716</y>
            </Vector2>
          </vertices>
        </world.shape.GDXPolygon>
        <world.shape.GDXPolygon>
          <name>Polygon-69</name>
          <resource>dirt1.png</resource>
          <density>1.0</density>
          <friction>0.5</friction>
          <restitution>0.3</restitution>
          <bodyType>StaticBody</bodyType>
          <center>
            <x>208.6957</x>
            <y>-47.36715</y>
          </center>
          <filter>
            <categoryBits>1</categoryBits>
            <maskBits>-1</maskBits>
            <groupIndex>0</groupIndex>
          </filter>
          <repeatable>true</repeatable>
          <vertices>
            <Vector2>
              <x>-20.579193</x>
              <y>-19.087914</y>
            </Vector2>
            <Vector2>
              <x>2.051941</x>
              <y>-10.29126</y>
            </Vector2>
            <Vector2>
              <x>-18.693268</x>
              <y>32.016464</y>
            </Vector2>
            <Vector2>
              <x>-16.380066</x>
              <y>32.03692</y>
            </Vector2>
            <Vector2>
              <x>-13.993179</x>
              <y>30.88825</y>
            </Vector2>
            <Vector2>
              <x>-12.053848</x>
              <y>29.56286</y>
            </Vector2>
            <Vector2>
              <x>-0.5669861</x>
              <y>19.092287</y>
            </Vector2>
            <Vector2>
              <x>3.9084015</x>
              <y>16.220612</y>
            </Vector2>
            <Vector2>
              <x>7.1903687</x>
              <y>15.911354</y>
            </Vector2>
            <Vector2>
              <x>12.1132965</x>
              <y>16.088074</y>
            </Vector2>
            <Vector2>
              <x>14.53746</x>
              <y>16.79495</y>
            </Vector2>
            <Vector2>
              <x>15.395248</x>
              <y>17.280926</y>
            </Vector2>
            <Vector2>
              <x>15.917374</x>
              <y>17.546003</y>
            </Vector2>
            <Vector2>
              <x>16.737854</x>
              <y>18.341238</y>
            </Vector2>
            <Vector2>
              <x>15.168869</x>
              <y>-115.779045</y>
            </Vector2>
            <Vector2>
              <x>-20.754074</x>
              <y>-116.62171</y>
            </Vector2>
          </vertices>
        </world.shape.GDXPolygon>
        <world.shape.GDXPolygon>
          <name>Polygon-92</name>
          <resource>dirt1.png</resource>
          <density>1.0</density>
          <friction>0.5</friction>
          <restitution>0.3</restitution>
          <bodyType>StaticBody</bodyType>
          <center>
            <x>247.45981</x>
            <y>-41.95771</y>
          </center>
          <filter>
            <categoryBits>1</categoryBits>
            <maskBits>-1</maskBits>
            <groupIndex>0</groupIndex>
          </filter>
          <repeatable>true</repeatable>
          <vertices>
            <Vector2>
              <x>-14.070831</x>
              <y>13.5422</y>
            </Vector2>
            <Vector2>
              <x>-13.107132</x>
              <y>12.759541</y>
            </Vector2>
            <Vector2>
              <x>-10.556534</x>
              <y>11.230618</y>
            </Vector2>
            <Vector2>
              <x>-8.65126</x>
              <y>10.065725</y>
            </Vector2>
            <Vector2>
              <x>-6.254303</x>
              <y>9.665295</y>
            </Vector2>
            <Vector2>
              <x>-3.888092</x>
              <y>9.628891</y>
            </Vector2>
            <Vector2>
              <x>-2.0135498</x>
              <y>9.95652</y>
            </Vector2>
            <Vector2>
              <x>-1.0609283</x>
              <y>10.356951</y>
            </Vector2>
            <Vector2>
              <x>0.44485474</x>
              <y>11.157814</y>
            </Vector2>
            <Vector2>
              <x>1.336029</x>
              <y>11.048609</y>
            </Vector2>
            <Vector2>
              <x>2.503769</x>
              <y>10.611774</y>
            </Vector2>
            <Vector2>
              <x>2.9339905</x>
              <y>10.029329</y>
            </Vector2>
            <Vector2>
              <x>3.5485992</x>
              <y>9.701702</y>
            </Vector2>
            <Vector2>
              <x>4.009552</x>
              <y>9.774509</y>
            </Vector2>
            <Vector2>
              <x>4.4705048</x>
              <y>10.029329</y>
            </Vector2>
            <Vector2>
              <x>4.99292</x>
              <y>10.538969</y>
            </Vector2>
            <Vector2>
              <x>5.361679</x>
              <y>10.902996</y>
            </Vector2>
            <Vector2>
              <x>5.4231415</x>
              <y>10.902996</y>
            </Vector2>
            <Vector2>
              <x>6.0991974</x>
              <y>10.648178</y>
            </Vector2>
            <Vector2>
              <x>6.56015</x>
              <y>9.992928</y>
            </Vector2>
            <Vector2>
              <x>6.8367157</x>
              <y>9.337673</y>
            </Vector2>
            <Vector2>
              <x>7.512787</x>
              <y>9.228466</y>
            </Vector2>
            <Vector2>
              <x>8.864899</x>
              <y>9.738106</y>
            </Vector2>
            <Vector2>
              <x>9.540955</x>
              <y>10.575371</y>
            </Vector2>
            <Vector2>
              <x>10.155579</x>
              <y>10.830193</y>
            </Vector2>
            <Vector2>
              <x>11.323303</x>
              <y>9.592495</y>
            </Vector2>
            <Vector2>
              <x>11.692078</x>
              <y>8.755226</y>
            </Vector2>
            <Vector2>
              <x>12.060852</x>
              <y>8.573212</y>
            </Vector2>
            <Vector2>
              <x>12.952026</x>
              <y>8.646019</y>
            </Vector2>
            <Vector2>
              <x>15.410431</x>
              <y>9.483284</y>
            </Vector2>
            <Vector2>
              <x>19.866272</x>
              <y>9.4104805</y>
            </Vector2>
            <Vector2>
              <x>21.93454</x>
              <y>-119.1329</y>
            </Vector2>
            <Vector2>
              <x>-24.550034</x>
              <y>-120.32479</y>
            </Vector2>
            <Vector2>
              <x>-22.94017</x>
              <y>-15.9146805</y>
            </Vector2>
            <Vector2>
              <x>-20.324158</x>
              <y>-22.589302</y>
            </Vector2>
            <Vector2>
              <x>-13.079819</x>
              <y>-23.781197</y>
            </Vector2>
            <Vector2>
              <x>-8.853943</x>
              <y>-20.44389</y>
            </Vector2>
            <Vector2>
              <x>-5.8354797</x>
              <y>-12.338993</y>
            </Vector2>
            <Vector2>
              <x>-11.067505</x>
              <y>1.2486305</y>
            </Vector2>
            <Vector2>
              <x>-14.8909</x>
              <y>5.301071</y>
            </Vector2>
            <Vector2>
              <x>-14.689667</x>
              <y>11.260557</y>
            </Vector2>
          </vertices>
        </world.shape.GDXPolygon>
        <world.shape.GDXPolygon>
          <name>Polygon-134</name>
          <resource>dirt1.png</resource>
          <density>1.0</density>
          <friction>0.5</friction>
          <restitution>0.3</restitution>
          <bodyType>StaticBody</bodyType>
          <center>
            <x>277.9704</x>
            <y>-33.774998</y>
          </center>
          <filter>
            <categoryBits>1</categoryBits>
            <maskBits>-1</maskBits>
            <groupIndex>0</groupIndex>
          </filter>
          <repeatable>true</repeatable>
          <vertices>
            <Vector2>
              <x>-10.570221</x>
              <y>-7.93182</y>
            </Vector2>
            <Vector2>
              <x>-5.6650085</x>
              <y>-7.7945595</y>
            </Vector2>
            <Vector2>
              <x>-5.935364</x>
              <y>12.108334</y>
            </Vector2>
            <Vector2>
              <x>-5.196686</x>
              <y>12.0811615</y>
            </Vector2>
            <Vector2>
              <x>-4.5231934</x>
              <y>11.875269</y>
            </Vector2>
            <Vector2>
              <x>-3.6976013</x>
              <y>11.386276</y>
            </Vector2>
            <Vector2>
              <x>-3.4368896</x>
              <y>11.12891</y>
            </Vector2>
            <Vector2>
              <x>-3.024109</x>
              <y>10.717125</y>
            </Vector2>
            <Vector2>
              <x>-2.480957</x>
              <y>10.305344</y>
            </Vector2>
            <Vector2>
              <x>-2.0898743</x>
              <y>10.047977</y>
            </Vector2>
            <Vector2>
              <x>-1.5684814</x>
              <y>9.764877</y>
            </Vector2>
            <Vector2>
              <x>-0.6125183</x>
              <y>9.404566</y>
            </Vector2>
            <Vector2>
              <x>0.73446655</x>
              <y>9.275883</y>
            </Vector2>
            <Vector2>
              <x>2.82016</x>
              <y>9.121464</y>
            </Vector2>
            <Vector2>
              <x>4.4792175</x>
              <y>9.331224</y>
            </Vector2>
            <Vector2>
              <x>5.327881</x>
              <y>9.771057</y>
            </Vector2>
            <Vector2>
              <x>6.4417725</x>
              <y>10.399393</y>
            </Vector2>
            <Vector2>
              <x>7.396515</x>
              <y>10.839226</y>
            </Vector2>
            <Vector2>
              <x>5.5400085</x>
              <y>3.0479012</y>
            </Vector2>
            <Vector2>
              <x>11.639801</x>
              <y>-1.3504295</y>
            </Vector2>
            <Vector2>
              <x>14.175873</x>
              <y>-76.519135</y>
            </Vector2>
            <Vector2>
              <x>-9.755035</x>
              <y>-77.01001</y>
            </Vector2>
          </vertices>
        </world.shape.GDXPolygon>
        <world.shape.GDXPolygon>
          <name>platform1</name>
          <resource>platform.png</resource>
          <density>1.0</density>
          <friction>0.5</friction>
          <restitution>0.3</restitution>
          <bodyType>DynamicBody</bodyType>
          <center>
            <x>269.61945</x>
            <y>-32.730988</y>
          </center>
          <filter>
            <categoryBits>1</categoryBits>
            <maskBits>-1</maskBits>
            <groupIndex>0</groupIndex>
          </filter>
          <repeatable>false</repeatable>
          <vertices>
            <Vector2>
              <x>-2.2302246</x>
              <y>0.17290878</y>
            </Vector2>
            <Vector2>
              <x>-2.2268066</x>
              <y>-0.11462402</y>
            </Vector2>
            <Vector2>
              <x>2.2011414</x>
              <y>-0.16353226</y>
            </Vector2>
            <Vector2>
              <x>2.255951</x>
              <y>0.10523605</y>
            </Vector2>
          </vertices>
        </world.shape.GDXPolygon>
        <world.shape.GDXPolygon>
          <name>Polygon-0</name>
          <resource>dirt1.png</resource>
          <density>1.0</density>
          <friction>0.5</friction>
          <restitution>0.3</restitution>
          <bodyType>StaticBody</bodyType>
          <center>
            <x>308.31018</x>
            <y>-47.248257</y>
          </center>
          <filter>
            <categoryBits>1</categoryBits>
            <maskBits>-1</maskBits>
            <groupIndex>0</groupIndex>
          </filter>
          <repeatable>true</repeatable>
          <vertices>
            <Vector2>
              <x>-16.4711</x>
              <y>21.005333</y>
            </Vector2>
            <Vector2>
              <x>-15.007141</x>
              <y>19.745062</y>
            </Vector2>
            <Vector2>
              <x>-13.765961</x>
              <y>18.981258</y>
            </Vector2>
            <Vector2>
              <x>-9.418304</x>
              <y>16.801413</y>
            </Vector2>
            <Vector2>
              <x>-2.3749695</x>
              <y>15.739382</y>
            </Vector2>
            <Vector2>
              <x>3.6727295</x>
              <y>15.827883</y>
            </Vector2>
            <Vector2>
              <x>5.2828674</x>
              <y>4.5860634</y>
            </Vector2>
            <Vector2>
              <x>8.024414</x>
              <y>3.0966911</y>
            </Vector2>
            <Vector2>
              <x>16.055237</x>
              <y>2.4280014</y>
            </Vector2>
            <Vector2>
              <x>16.776367</x>
              <y>3.0180206</y>
            </Vector2>
            <Vector2>
              <x>19.300323</x>
              <y>3.6080399</y>
            </Vector2>
            <Vector2>
              <x>24.845642</x>
              <y>-68.772</y>
            </Vector2>
            <Vector2>
              <x>-17.257141</x>
              <y>-67.97005</y>
            </Vector2>
            <Vector2>
              <x>-19.663025</x>
              <y>11.904957</y>
            </Vector2>
          </vertices>
        </world.shape.GDXPolygon>
        <world.shape.GDXPolygon>
          <name>fallout1</name>
          <resource>platform.png</resource>
          <density>1.0</density>
          <friction>0.5</friction>
          <restitution>0.3</restitution>
          <bodyType>StaticBody</bodyType>
          <center>
            <x>314.33432</x>
            <y>-31.592075</y>
          </center>
          <filter>
            <categoryBits>1</categoryBits>
            <maskBits>-1</maskBits>
            <groupIndex>0</groupIndex>
          </filter>
          <repeatable>false</repeatable>
          <vertices>
            <Vector2>
              <x>-2.1948547</x>
              <y>0.13185883</y>
            </Vector2>
            <Vector2>
              <x>2.1892395</x>
              <y>0.13185883</y>
            </Vector2>
            <Vector2>
              <x>2.110321</x>
              <y>-0.12509918</y>
            </Vector2>
            <Vector2>
              <x>-2.1047058</x>
              <y>-0.13862228</y>
            </Vector2>
          </vertices>
        </world.shape.GDXPolygon>
        <world.shape.GDXPolygon>
          <name>fallout2</name>
          <resource>platform.png</resource>
          <density>1.0</density>
          <friction>0.5</friction>
          <restitution>0.3</restitution>
          <bodyType>StaticBody</bodyType>
          <center>
            <x>318.8262</x>
            <y>-31.55909</y>
          </center>
          <filter>
            <categoryBits>1</categoryBits>
            <maskBits>-1</maskBits>
            <groupIndex>0</groupIndex>
          </filter>
          <repeatable>false</repeatable>
          <vertices>
            <Vector2>
              <x>-2.2538452</x>
              <y>0.09091377</y>
            </Vector2>
            <Vector2>
              <x>-2.1889038</x>
              <y>-0.14286041</y>
            </Vector2>
            <Vector2>
              <x>2.1835327</x>
              <y>-0.09090996</y>
            </Vector2>
            <Vector2>
              <x>2.2592773</x>
              <y>0.14286423</y>
            </Vector2>
          </vertices>
        </world.shape.GDXPolygon>
        <world.shape.GDXPolygon>
          <name>Polygon-28</name>
          <resource>dirt1.png</resource>
          <density>1.0</density>
          <friction>0.5</friction>
          <restitution>0.3</restitution>
          <bodyType>StaticBody</bodyType>
          <center>
            <x>316.3099</x>
            <y>-32.144363</y>
          </center>
          <filter>
            <categoryBits>1</categoryBits>
            <maskBits>-1</maskBits>
            <groupIndex>0</groupIndex>
          </filter>
          <repeatable>true</repeatable>
          <vertices>
            <Vector2>
              <x>0.19210815</x>
              <y>0.43429184</y>
            </Vector2>
            <Vector2>
              <x>-0.259552</x>
              <y>-0.07848358</y>
            </Vector2>
            <Vector2>
              <x>-0.1305542</x>
              <y>-0.22319794</y>
            </Vector2>
            <Vector2>
              <x>0.19799805</x>
              <y>-0.13261414</y>
            </Vector2>
          </vertices>
        </world.shape.GDXPolygon>
        <world.shape.GDXPolygon>
          <name>Polygon-32</name>
          <resource>dirt1.png</resource>
          <density>1.0</density>
          <friction>0.5</friction>
          <restitution>0.3</restitution>
          <bodyType>StaticBody</bodyType>
          <center>
            <x>321.00897</x>
            <y>-31.967333</y>
          </center>
          <filter>
            <categoryBits>1</categoryBits>
            <maskBits>-1</maskBits>
            <groupIndex>0</groupIndex>
          </filter>
          <repeatable>true</repeatable>
          <vertices>
            <Vector2>
              <x>0.071136475</x>
              <y>0.34493256</y>
            </Vector2>
            <Vector2>
              <x>-0.15097046</x>
              <y>-0.008041382</y>
            </Vector2>
            <Vector2>
              <x>-0.014099121</x>
              <y>-0.1664486</y>
            </Vector2>
            <Vector2>
              <x>0.093933105</x>
              <y>-0.1704464</y>
            </Vector2>
          </vertices>
        </world.shape.GDXPolygon>
        <world.shape.GDXPolygon>
          <name>fallout3</name>
          <resource>platform.png</resource>
          <density>1.0</density>
          <friction>0.5</friction>
          <restitution>0.3</restitution>
          <bodyType>StaticBody</bodyType>
          <center>
            <x>323.33524</x>
            <y>-31.50919</y>
          </center>
          <filter>
            <categoryBits>1</categoryBits>
            <maskBits>-1</maskBits>
            <groupIndex>0</groupIndex>
          </filter>
          <repeatable>false</repeatable>
          <vertices>
            <Vector2>
              <x>-2.2025452</x>
              <y>0.07495117</y>
            </Vector2>
            <Vector2>
              <x>2.184204</x>
              <y>0.13667488</y>
            </Vector2>
            <Vector2>
              <x>2.1401367</x>
              <y>-0.08376503</y>
            </Vector2>
            <Vector2>
              <x>-2.1217346</x>
              <y>-0.1278534</y>
            </Vector2>
          </vertices>
        </world.shape.GDXPolygon>
        <world.shape.GDXPolygon>
          <name>Polygon-45</name>
          <resource>dirt1.png</resource>
          <density>1.0</density>
          <friction>0.5</friction>
          <restitution>0.3</restitution>
          <bodyType>StaticBody</bodyType>
          <center>
            <x>325.54694</x>
            <y>-32.085407</y>
          </center>
          <filter>
            <categoryBits>1</categoryBits>
            <maskBits>-1</maskBits>
            <groupIndex>0</groupIndex>
          </filter>
          <repeatable>true</repeatable>
          <vertices>
            <Vector2>
              <x>0.09265137</x>
              <y>0.5168133</y>
            </Vector2>
            <Vector2>
              <x>-0.24783325</x>
              <y>-0.06916046</y>
            </Vector2>
            <Vector2>
              <x>-0.04284668</x>
              <y>-0.30511856</y>
            </Vector2>
            <Vector2>
              <x>0.19802856</x>
              <y>-0.14253998</y>
            </Vector2>
          </vertices>
        </world.shape.GDXPolygon>
        <world.shape.GDXPolygon>
          <name>Polygon-0</name>
          <resource>dirt1.png</resource>
          <density>1.0</density>
          <friction>0.5</friction>
          <restitution>0.3</restitution>
          <bodyType>StaticBody</bodyType>
          <center>
            <x>363.3047</x>
            <y>-43.488926</y>
          </center>
          <filter>
            <categoryBits>1</categoryBits>
            <maskBits>-1</maskBits>
            <groupIndex>0</groupIndex>
          </filter>
          <repeatable>true</repeatable>
          <vertices>
            <Vector2>
              <x>-32.81488</x>
              <y>11.207821</y>
            </Vector2>
            <Vector2>
              <x>-30.523468</x>
              <y>11.654644</y>
            </Vector2>
            <Vector2>
              <x>-26.427582</x>
              <y>11.654644</y>
            </Vector2>
            <Vector2>
              <x>-22.517883</x>
              <y>11.035969</y>
            </Vector2>
            <Vector2>
              <x>-18.485321</x>
              <y>9.879009</y>
            </Vector2>
            <Vector2>
              <x>-11.470673</x>
              <y>8.462967</y>
            </Vector2>
            <Vector2>
              <x>-5.1115723</x>
              <y>7.1649323</y>
            </Vector2>
            <Vector2>
              <x>0.100250244</x>
              <y>6.024231</y>
            </Vector2>
            <Vector2>
              <x>3.7387085</x>
              <y>6.417576</y>
            </Vector2>
            <Vector2>
              <x>9.901123</x>
              <y>8.108959</y>
            </Vector2>
            <Vector2>
              <x>14.817932</x>
              <y>10.233025</y>
            </Vector2>
            <Vector2>
              <x>18.718597</x>
              <y>11.806406</y>
            </Vector2>
            <Vector2>
              <x>25.569336</x>
              <y>12.986441</y>
            </Vector2>
            <Vector2>
              <x>31.207306</x>
              <y>10.82304</y>
            </Vector2>
            <Vector2>
              <x>34.812958</x>
              <y>7.4402733</y>
            </Vector2>
            <Vector2>
              <x>37.664703</x>
              <y>4.9621964</y>
            </Vector2>
            <Vector2>
              <x>38.77884</x>
              <y>-77.46309</y>
            </Vector2>
            <Vector2>
              <x>-31.556763</x>
              <y>-71.83624</y>
            </Vector2>
            <Vector2>
              <x>-36.4021</x>
              <y>-0.562809</y>
            </Vector2>
          </vertices>
        </world.shape.GDXPolygon>
        <world.shape.GDXPolygon>
          <name>Polygon-19</name>
          <resource>dirt1.png</resource>
          <density>1.0</density>
          <friction>0.5</friction>
          <restitution>0.3</restitution>
          <bodyType>StaticBody</bodyType>
          <center>
            <x>443.46658</x>
            <y>-50.77817</y>
          </center>
          <filter>
            <categoryBits>1</categoryBits>
            <maskBits>-1</maskBits>
            <groupIndex>0</groupIndex>
          </filter>
          <repeatable>true</repeatable>
          <vertices>
            <Vector2>
              <x>-42.548737</x>
              <y>12.220341</y>
            </Vector2>
            <Vector2>
              <x>-33.331055</x>
              <y>7.049389</y>
            </Vector2>
            <Vector2>
              <x>-23.618835</x>
              <y>4.873848</y>
            </Vector2>
            <Vector2>
              <x>-12.352631</x>
              <y>6.8939934</y>
            </Vector2>
            <Vector2>
              <x>-6.395813</x>
              <y>10.157303</y>
            </Vector2>
            <Vector2>
              <x>-2.5109253</x>
              <y>14.819176</y>
            </Vector2>
            <Vector2>
              <x>4.3523865</x>
              <y>18.704063</y>
            </Vector2>
            <Vector2>
              <x>11.38562</x>
              <y>18.91773</y>
            </Vector2>
            <Vector2>
              <x>38.337067</x>
              <y>18.480679</y>
            </Vector2>
            <Vector2>
              <x>38.26422</x>
              <y>26.347588</y>
            </Vector2>
            <Vector2>
              <x>40.376648</x>
              <y>26.260178</y>
            </Vector2>
            <Vector2>
              <x>32.0831</x>
              <y>-97.195526</y>
            </Vector2>
            <Vector2>
              <x>-44.04135</x>
              <y>-67.52881</y>
            </Vector2>
          </vertices>
        </world.shape.GDXPolygon>
        <world.shape.GDXPolygon>
          <name>platform2</name>
          <resource>platform.png</resource>
          <density>1.0</density>
          <friction>0.5</friction>
          <restitution>0.3</restitution>
          <bodyType>DynamicBody</bodyType>
          <center>
            <x>479.37738</x>
            <y>-32.024536</y>
          </center>
          <filter>
            <categoryBits>1</categoryBits>
            <maskBits>-1</maskBits>
            <groupIndex>0</groupIndex>
          </filter>
          <repeatable>false</repeatable>
          <vertices>
            <Vector2>
              <x>-2.1859436</x>
              <y>0.105731964</y>
            </Vector2>
            <Vector2>
              <x>2.1943665</x>
              <y>0.14600945</y>
            </Vector2>
            <Vector2>
              <x>2.110443</x>
              <y>-0.13593864</y>
            </Vector2>
            <Vector2>
              <x>-2.118805</x>
              <y>-0.11580086</y>
            </Vector2>
          </vertices>
        </world.shape.GDXPolygon>
        <world.shape.GDXPolygon>
          <name>Polygon-39</name>
          <resource>dirt1.png</resource>
          <density>1.0</density>
          <friction>0.5</friction>
          <restitution>0.3</restitution>
          <bodyType>StaticBody</bodyType>
          <center>
            <x>533.22565</x>
            <y>-0.23786508</y>
          </center>
          <filter>
            <categoryBits>1</categoryBits>
            <maskBits>-1</maskBits>
            <groupIndex>0</groupIndex>
          </filter>
          <repeatable>true</repeatable>
          <vertices>
            <Vector2>
              <x>-51.914032</x>
              <y>7.8947964</y>
            </Vector2>
            <Vector2>
              <x>-39.62198</x>
              <y>7.741143</y>
            </Vector2>
            <Vector2>
              <x>-37.76538</x>
              <y>7.126544</y>
            </Vector2>
            <Vector2>
              <x>-36.613007</x>
              <y>5.974162</y>
            </Vector2>
            <Vector2>
              <x>-34.180206</x>
              <y>3.208456</y>
            </Vector2>
            <Vector2>
              <x>-33.283905</x>
              <y>2.593852</y>
            </Vector2>
            <Vector2>
              <x>-32.067505</x>
              <y>0.44274533</y>
            </Vector2>
            <Vector2>
              <x>-30.338928</x>
              <y>-0.1718582</y>
            </Vector2>
            <Vector2>
              <x>-28.162231</x>
              <y>-0.6328081</y>
            </Vector2>
            <Vector2>
              <x>-26.177582</x>
              <y>-0.8632859</y>
            </Vector2>
            <Vector2>
              <x>-25.217255</x>
              <y>-0.8632859</y>
            </Vector2>
            <Vector2>
              <x>-23.040527</x>
              <y>-0.4791597</y>
            </Vector2>
            <Vector2>
              <x>-19.839478</x>
              <y>0.44274533</y>
            </Vector2>
            <Vector2>
              <x>-17.534729</x>
              <y>1.134173</y>
            </Vector2>
            <Vector2>
              <x>-16.062256</x>
              <y>1.5951272</y>
            </Vector2>
            <Vector2>
              <x>-14.269653</x>
              <y>2.2865548</y>
            </Vector2>
            <Vector2>
              <x>-12.221008</x>
              <y>3.2084556</y>
            </Vector2>
            <Vector2>
              <x>-10.36438</x>
              <y>4.8986125</y>
            </Vector2>
            <Vector2>
              <x>-8.955933</x>
              <y>6.358292</y>
            </Vector2>
            <Vector2>
              <x>-6.4591064</x>
              <y>7.587498</y>
            </Vector2>
            <Vector2>
              <x>-4.154358</x>
              <y>6.742418</y>
            </Vector2>
            <Vector2>
              <x>-2.6818848</x>
              <y>5.743693</y>
            </Vector2>
            <Vector2>
              <x>-1.2094116</x>
              <y>4.4376616</y>
            </Vector2>
            <Vector2>
              <x>0.19909668</x>
              <y>2.363379</y>
            </Vector2>
            <Vector2>
              <x>1.5435181</x>
              <y>0.75004685</y>
            </Vector2>
            <Vector2>
              <x>3.3361206</x>
              <y>-0.47915542</y>
            </Vector2>
            <Vector2>
              <x>4.3604126</x>
              <y>-1.1705831</y>
            </Vector2>
            <Vector2>
              <x>6.729248</x>
              <y>-0.7864572</y>
            </Vector2>
            <Vector2>
              <x>10.570496</x>
              <y>0.5195738</y>
            </Vector2>
            <Vector2>
              <x>13.38739</x>
              <y>2.363379</y>
            </Vector2>
            <Vector2>
              <x>15.564148</x>
              <y>4.2840095</y>
            </Vector2>
            <Vector2>
              <x>17.612793</x>
              <y>5.5132155</y>
            </Vector2>
            <Vector2>
              <x>18.957214</x>
              <y>5.820517</y>
            </Vector2>
            <Vector2>
              <x>19.277344</x>
              <y>5.5132155</y>
            </Vector2>
            <Vector2>
              <x>20.365723</x>
              <y>3.5925813</y>
            </Vector2>
            <Vector2>
              <x>21.582092</x>
              <y>0.8268753</y>
            </Vector2>
            <Vector2>
              <x>22.22229</x>
              <y>-0.7864572</y>
            </Vector2>
            <Vector2>
              <x>22.862549</x>
              <y>-1.6315333</y>
            </Vector2>
            <Vector2>
              <x>24.078918</x>
              <y>-2.322961</y>
            </Vector2>
            <Vector2>
              <x>25.935547</x>
              <y>-2.3997855</y>
            </Vector2>
            <Vector2>
              <x>27.664062</x>
              <y>-2.3229616</y>
            </Vector2>
            <Vector2>
              <x>31.82544</x>
              <y>-2.3229616</y>
            </Vector2>
            <Vector2>
              <x>33.81012</x>
              <y>-0.70963347</y>
            </Vector2>
            <Vector2>
              <x>34.962463</x>
              <y>1.6719514</y>
            </Vector2>
            <Vector2>
              <x>36.627014</x>
              <y>3.2852793</y>
            </Vector2>
            <Vector2>
              <x>38.80371</x>
              <y>3.8998823</y>
            </Vector2>
            <Vector2>
              <x>42.388916</x>
              <y>3.976707</y>
            </Vector2>
            <Vector2>
              <x>50.26349</x>
              <y>3.6694098</y>
            </Vector2>
            <Vector2>
              <x>49.942444</x>
              <y>-9.330872</y>
            </Vector2>
            <Vector2>
              <x>49.06714</x>
              <y>-11.131468</y>
            </Vector2>
            <Vector2>
              <x>45.69104</x>
              <y>-13.382206</y>
            </Vector2>
            <Vector2>
              <x>44.690735</x>
              <y>-13.832348</y>
            </Vector2>
            <Vector2>
              <x>39.689087</x>
              <y>-14.432547</y>
            </Vector2>
            <Vector2>
              <x>35.687744</x>
              <y>-14.432547</y>
            </Vector2>
            <Vector2>
              <x>29.810852</x>
              <y>-14.432547</y>
            </Vector2>
            <Vector2>
              <x>16.181335</x>
              <y>-14.282499</y>
            </Vector2>
            <Vector2>
              <x>-41.212524</x>
              <y>-7.6803327</y>
            </Vector2>
            <Vector2>
              <x>-47.33954</x>
              <y>-4.3792424</y>
            </Vector2>
            <Vector2>
              <x>-49.09012</x>
              <y>-3.1788487</y>
            </Vector2>
            <Vector2>
              <x>-50.8407</x>
              <y>-1.0781559</y>
            </Vector2>
            <Vector2>
              <x>-51.44754</x>
              <y>1.5596075</y>
            </Vector2>
            <Vector2>
              <x>-51.798065</x>
              <y>4.5239234</y>
            </Vector2>
            <Vector2>
              <x>-51.83142</x>
              <y>5.966024</y>
            </Vector2>
          </vertices>
        </world.shape.GDXPolygon>
        <world.shape.GDXPolygon>
          <name>Polygon-106</name>
          <resource>dirt1.png</resource>
          <density>1.0</density>
          <friction>0.5</friction>
          <restitution>0.3</restitution>
          <bodyType>StaticBody</bodyType>
          <center>
            <x>659.36163</x>
            <y>-67.75024</y>
          </center>
          <filter>
            <categoryBits>1</categoryBits>
            <maskBits>-1</maskBits>
            <groupIndex>0</groupIndex>
          </filter>
          <repeatable>true</repeatable>
          <vertices>
            <Vector2>
              <x>-185.33536</x>
              <y>-39.17476</y>
            </Vector2>
            <Vector2>
              <x>-40.53302</x>
              <y>-40.559227</y>
            </Vector2>
            <Vector2>
              <x>-49.762695</x>
              <y>27.934525</y>
            </Vector2>
            <Vector2>
              <x>-48.19995</x>
              <y>27.68177</y>
            </Vector2>
            <Vector2>
              <x>-46.662964</x>
              <y>26.944004</y>
            </Vector2>
            <Vector2>
              <x>-45.279663</x>
              <y>25.83736</y>
            </Vector2>
            <Vector2>
              <x>-44.588013</x>
              <y>24.546272</y>
            </Vector2>
            <Vector2>
              <x>-43.3584</x>
              <y>22.609634</y>
            </Vector2>
            <Vector2>
              <x>-42.05194</x>
              <y>20.949665</y>
            </Vector2>
            <Vector2>
              <x>-39.7464</x>
              <y>18.73637</y>
            </Vector2>
            <Vector2>
              <x>-35.827026</x>
              <y>16.707512</y>
            </Vector2>
            <Vector2>
              <x>-32.676147</x>
              <y>15.785309</y>
            </Vector2>
            <Vector2>
              <x>-30.370667</x>
              <y>15.969753</y>
            </Vector2>
            <Vector2>
              <x>-26.37439</x>
              <y>17.260841</y>
            </Vector2>
            <Vector2>
              <x>-23.607788</x>
              <y>18.82859</y>
            </Vector2>
            <Vector2>
              <x>-21.993958</x>
              <y>20.119678</y>
            </Vector2>
            <Vector2>
              <x>-20.303223</x>
              <y>21.50299</y>
            </Vector2>
            <Vector2>
              <x>-19.304138</x>
              <y>22.332977</y>
            </Vector2>
            <Vector2>
              <x>-17.76715</x>
              <y>22.332977</y>
            </Vector2>
            <Vector2>
              <x>-16.38385</x>
              <y>21.595211</y>
            </Vector2>
            <Vector2>
              <x>-15.615356</x>
              <y>20.673004</y>
            </Vector2>
            <Vector2>
              <x>-14.462585</x>
              <y>18.275265</y>
            </Vector2>
            <Vector2>
              <x>-13.770935</x>
              <y>17.168617</y>
            </Vector2>
            <Vector2>
              <x>-12.0802</x>
              <y>16.06197</y>
            </Vector2>
            <Vector2>
              <x>-11.311707</x>
              <y>15.231987</y>
            </Vector2>
            <Vector2>
              <x>-7.930298</x>
              <y>13.572014</y>
            </Vector2>
            <Vector2>
              <x>-4.164612</x>
              <y>11.358719</y>
            </Vector2>
            <Vector2>
              <x>-2.2433472</x>
              <y>10.252071</y>
            </Vector2>
            <Vector2>
              <x>-1.0137329</x>
              <y>9.606525</y>
            </Vector2>
            <Vector2>
              <x>0.44641113</x>
              <y>8.868763</y>
            </Vector2>
            <Vector2>
              <x>1.9834595</x>
              <y>8.223217</y>
            </Vector2>
            <Vector2>
              <x>2.8287964</x>
              <y>7.301014</y>
            </Vector2>
            <Vector2>
              <x>3.7509766</x>
              <y>6.4710274</y>
            </Vector2>
            <Vector2>
              <x>5.7490845</x>
              <y>5.087719</y>
            </Vector2>
            <Vector2>
              <x>9.361084</x>
              <y>2.5055466</y>
            </Vector2>
            <Vector2>
              <x>11.581238</x>
              <y>0.44274902</y>
            </Vector2>
            <Vector2>
              <x>15.514709</x>
              <y>-4.749405</y>
            </Vector2>
            <Vector2>
              <x>18.268127</x>
              <y>-9.259766</y>
            </Vector2>
            <Vector2>
              <x>19.229675</x>
              <y>-10.518471</y>
            </Vector2>
            <Vector2>
              <x>20.278564</x>
              <y>-11.56739</y>
            </Vector2>
            <Vector2>
              <x>22.070496</x>
              <y>-12.09185</y>
            </Vector2>
            <Vector2>
              <x>23.425354</x>
              <y>-12.35408</y>
            </Vector2>
            <Vector2>
              <x>24.955017</x>
              <y>-11.934509</y>
            </Vector2>
            <Vector2>
              <x>26.921753</x>
              <y>-10.728256</y>
            </Vector2>
            <Vector2>
              <x>28.801025</x>
              <y>-9.31221</y>
            </Vector2>
            <Vector2>
              <x>29.63147</x>
              <y>-7.791275</y>
            </Vector2>
            <Vector2>
              <x>30.680359</x>
              <y>-7.791275</y>
            </Vector2>
            <Vector2>
              <x>31.860413</x>
              <y>-8.105949</y>
            </Vector2>
            <Vector2>
              <x>33.415283</x>
              <y>-8.192055</y>
            </Vector2>
            <Vector2>
              <x>35.567078</x>
              <y>-9.298706</y>
            </Vector2>
            <Vector2>
              <x>38.56427</x>
              <y>-10.774231</y>
            </Vector2>
            <Vector2>
              <x>41.561462</x>
              <y>-12.065323</y>
            </Vector2>
            <Vector2>
              <x>48.247437</x>
              <y>-13.540855</y>
            </Vector2>
            <Vector2>
              <x>57.238953</x>
              <y>-14.001961</y>
            </Vector2>
            <Vector2>
              <x>71.91742</x>
              <y>-15.846367</y>
            </Vector2>
            <Vector2>
              <x>83.75238</x>
              <y>-16.584137</y>
            </Vector2>
            <Vector2>
              <x>93.43555</x>
              <y>-16.584137</y>
            </Vector2>
            <Vector2>
              <x>157.21216</x>
              <y>-16.444313</y>
            </Vector2>
            <Vector2>
              <x>112.663574</x>
              <y>-110.26002</y>
            </Vector2>
            <Vector2>
              <x>-188.19562</x>
              <y>-119.244835</y>
            </Vector2>
          </vertices>
        </world.shape.GDXPolygon>
      </polygons>
      <npcs/>
      <paths/>
      <joints>
        <world.joint.PrismaticJoint>
          <name>platform1Joint</name>
          <bodyA>platform1</bodyA>
          <bodyB>Polygon-134</bodyB>
          <jointType>PrismaticJoint</jointType>
          <collideConnected>false</collideConnected>
          <enableLimit>false</enableLimit>
          <enableMotor>true</enableMotor>
          <lowerTranslation>0.0</lowerTranslation>
          <upperTranslation>0.0</upperTranslation>
          <maxMotorForce>999.0</maxMotorForce>
          <motorSpeed>1.0</motorSpeed>
          <referenceAngle>0.0</referenceAngle>
          <anchor>
            <x>280.44656</x>
            <y>-32.426334</y>
          </anchor>
          <axis>
            <x>0.0</x>
            <y>-1.0</y>
          </axis>
        </world.joint.PrismaticJoint>
        <world.joint.RevoluteJoint>
          <name>fallout1Joint</name>
          <bodyA>fallout1</bodyA>
          <bodyB>Polygon-28</bodyB>
          <jointType>RevoluteJoint</jointType>
          <collideConnected>false</collideConnected>
          <enableLimit>false</enableLimit>
          <enableMotor>false</enableMotor>
          <lowerAngle>0.0</lowerAngle>
          <upperAngle>0.0</upperAngle>
          <maxMotorTorque>0.0</maxMotorTorque>
          <motorSpeed>0.0</motorSpeed>
          <referenceAngle>0.0</referenceAngle>
          <anchor>
            <x>316.39996</x>
            <y>-31.65275</y>
          </anchor>
        </world.joint.RevoluteJoint>
        <world.joint.RevoluteJoint>
          <name>fallout2Joint</name>
          <bodyA>Polygon-32</bodyA>
          <bodyB>fallout2</bodyB>
          <jointType>RevoluteJoint</jointType>
          <collideConnected>false</collideConnected>
          <enableLimit>false</enableLimit>
          <enableMotor>false</enableMotor>
          <lowerAngle>0.0</lowerAngle>
          <upperAngle>0.0</upperAngle>
          <maxMotorTorque>0.0</maxMotorTorque>
          <motorSpeed>0.0</motorSpeed>
          <referenceAngle>0.0</referenceAngle>
          <anchor>
            <x>321.03314</x>
            <y>-31.541492</y>
          </anchor>
        </world.joint.RevoluteJoint>
        <world.joint.RevoluteJoint>
          <name>fallout3Joint</name>
          <bodyA>Polygon-45</bodyA>
          <bodyB>fallout3</bodyB>
          <jointType>RevoluteJoint</jointType>
          <collideConnected>false</collideConnected>
          <enableLimit>false</enableLimit>
          <enableMotor>false</enableMotor>
          <lowerAngle>0.0</lowerAngle>
          <upperAngle>0.0</upperAngle>
          <maxMotorTorque>0.0</maxMotorTorque>
          <motorSpeed>0.0</motorSpeed>
          <referenceAngle>0.0</referenceAngle>
          <anchor>
            <x>325.4437</x>
            <y>-31.485794</y>
          </anchor>
        </world.joint.RevoluteJoint>
        <world.joint.PrismaticJoint>
          <name>platform2Joint</name>
          <bodyA>platform2</bodyA>
          <bodyB>Polygon-39</bodyB>
          <jointType>PrismaticJoint</jointType>
          <collideConnected>false</collideConnected>
          <enableLimit>false</enableLimit>
          <enableMotor>false</enableMotor>
          <lowerTranslation>0.0</lowerTranslation>
          <upperTranslation>0.0</upperTranslation>
          <maxMotorForce>0.0</maxMotorForce>
          <motorSpeed>0.0</motorSpeed>
          <referenceAngle>0.0</referenceAngle>
          <anchor>
            <x>479.3592</x>
            <y>-32.102505</y>
          </anchor>
          <axis>
            <x>0.0</x>
            <y>-1.0</y>
          </axis>
        </world.joint.PrismaticJoint>
      </joints>
      <quests>
        <world.quest.GDXQuest>
          <name>Quest-16</name>
          <prerequisites></prerequisites>
          <repeatable>false</repeatable>
          <trigger class="plugin.quest.trigger.activate.ActivateTrigger"/>
          <manifestation class="com.blastedstudios.velocitystack.quest.moneybag.MoneyBagManifestation">
            <position>
              <x>94.78334</x>
              <y>2.2803571</y>
            </position>
            <amount>50</amount>
          </manifestation>
        </world.quest.GDXQuest>
        <world.quest.GDXQuest>
          <name>Quest-17</name>
          <prerequisites></prerequisites>
          <repeatable>false</repeatable>
          <trigger class="plugin.quest.trigger.activate.ActivateTrigger"/>
          <manifestation class="com.blastedstudios.velocitystack.quest.moneybag.MoneyBagManifestation">
            <position>
              <x>103.083336</x>
              <y>-0.20730406</y>
            </position>
            <amount>50</amount>
          </manifestation>
        </world.quest.GDXQuest>
        <world.quest.GDXQuest>
          <name>Quest-18</name>
          <prerequisites></prerequisites>
          <repeatable>false</repeatable>
          <trigger class="plugin.quest.trigger.activate.ActivateTrigger"/>
          <manifestation class="com.blastedstudios.velocitystack.quest.moneybag.MoneyBagManifestation">
            <position>
              <x>105.58334</x>
              <y>-3.0</y>
            </position>
            <amount>50</amount>
          </manifestation>
        </world.quest.GDXQuest>
        <world.quest.GDXQuest>
          <name>Quest-31</name>
          <prerequisites></prerequisites>
          <repeatable>false</repeatable>
          <trigger class="plugin.quest.trigger.activate.ActivateTrigger"/>
          <manifestation class="com.blastedstudios.velocitystack.quest.moneybag.MoneyBagManifestation">
            <position>
              <x>187.83546</x>
              <y>-14.30964</y>
            </position>
            <amount>50</amount>
          </manifestation>
        </world.quest.GDXQuest>
        <world.quest.GDXQuest>
          <name>Quest-32</name>
          <prerequisites></prerequisites>
          <repeatable>false</repeatable>
          <trigger class="plugin.quest.trigger.activate.ActivateTrigger"/>
          <manifestation class="com.blastedstudios.velocitystack.quest.moneybag.MoneyBagManifestation">
            <position>
              <x>188.8946</x>
              <y>-11.414285</y>
            </position>
            <amount>50</amount>
          </manifestation>
        </world.quest.GDXQuest>
        <world.quest.GDXQuest>
          <name>Quest-33</name>
          <prerequisites></prerequisites>
          <repeatable>false</repeatable>
          <trigger class="plugin.quest.trigger.activate.ActivateTrigger"/>
          <manifestation class="com.blastedstudios.velocitystack.quest.moneybag.MoneyBagManifestation">
            <position>
              <x>192.2146</x>
              <y>-13.416906</y>
            </position>
            <amount>50</amount>
          </manifestation>
        </world.quest.GDXQuest>
        <world.quest.GDXQuest>
          <name>Quest-34</name>
          <prerequisites></prerequisites>
          <repeatable>false</repeatable>
          <trigger class="plugin.quest.trigger.activate.ActivateTrigger"/>
          <manifestation class="com.blastedstudios.velocitystack.quest.moneybag.MoneyBagManifestation">
            <position>
              <x>228.07883</x>
              <y>-25.876045</y>
            </position>
            <amount>50</amount>
          </manifestation>
        </world.quest.GDXQuest>
        <world.quest.GDXQuest>
          <name>Quest-36</name>
          <prerequisites></prerequisites>
          <repeatable>false</repeatable>
          <trigger class="plugin.quest.trigger.activate.ActivateTrigger"/>
          <manifestation class="com.blastedstudios.velocitystack.quest.moneybag.MoneyBagManifestation">
            <position>
              <x>230.6159</x>
              <y>-24.827642</y>
            </position>
            <amount>50</amount>
          </manifestation>
        </world.quest.GDXQuest>
        <world.quest.GDXQuest>
          <name>Quest-37</name>
          <prerequisites></prerequisites>
          <repeatable>false</repeatable>
          <trigger class="plugin.quest.trigger.activate.ActivateTrigger"/>
          <manifestation class="com.blastedstudios.velocitystack.quest.moneybag.MoneyBagManifestation">
            <position>
              <x>233.743</x>
              <y>-26.924448</y>
            </position>
            <amount>50</amount>
          </manifestation>
        </world.quest.GDXQuest>
        <world.quest.GDXQuest>
          <name>platform1</name>
          <prerequisites></prerequisites>
          <repeatable>false</repeatable>
          <trigger class="plugin.quest.trigger.activate.ActivateTrigger"/>
          <manifestation class="plugin.quest.manifestation.platform.PlatformManifestation">
            <name>platform1</name>
            <joint>platform1Joint</joint>
            <pointA>
              <x>269.59573</x>
              <y>-37.789352</y>
            </pointA>
            <pointB>
              <x>269.85638</x>
              <y>-16.943787</y>
            </pointB>
            <waitDuration>5000</waitDuration>
            <maxMotorForceA>999.0</maxMotorForceA>
            <motorSpeedA>-3.0</motorSpeedA>
            <maxMotorForceB>999.0</maxMotorForceB>
            <motorSpeedB>3.0</motorSpeedB>
          </manifestation>
        </world.quest.GDXQuest>
        <world.quest.GDXQuest>
          <name>start</name>
          <prerequisites></prerequisites>
          <repeatable>false</repeatable>
          <trigger class="plugin.quest.trigger.activate.ActivateTrigger"/>
          <manifestation class="plugin.quest.manifestation.beingspawn.BeingSpawnManifestation">
            <coordinates>
              <x>0.0</x>
              <y>0.0</y>
            </coordinates>
            <being>player</being>
            <path></path>
          </manifestation>
        </world.quest.GDXQuest>
        <world.quest.GDXQuest>
          <name>Quest-154</name>
          <prerequisites></prerequisites>
          <repeatable>false</repeatable>
          <trigger class="plugin.quest.trigger.activate.ActivateTrigger"/>
          <manifestation class="com.blastedstudios.velocitystack.quest.moneybag.MoneyBagManifestation">
            <position>
              <x>288.12762</x>
              <y>-21.285046</y>
            </position>
            <amount>50</amount>
          </manifestation>
        </world.quest.GDXQuest>
        <world.quest.GDXQuest>
          <name>Quest-155</name>
          <prerequisites></prerequisites>
          <repeatable>false</repeatable>
          <trigger class="plugin.quest.trigger.activate.ActivateTrigger"/>
          <manifestation class="com.blastedstudios.velocitystack.quest.moneybag.MoneyBagManifestation">
            <position>
              <x>295.46558</x>
              <y>-23.744461</y>
            </position>
            <amount>50</amount>
          </manifestation>
        </world.quest.GDXQuest>
        <world.quest.GDXQuest>
          <name>Quest-156</name>
          <prerequisites></prerequisites>
          <repeatable>false</repeatable>
          <trigger class="plugin.quest.trigger.activate.ActivateTrigger"/>
          <manifestation class="com.blastedstudios.velocitystack.quest.moneybag.MoneyBagManifestation">
            <position>
              <x>299.24045</x>
              <y>-26.35157</y>
            </position>
            <amount>50</amount>
          </manifestation>
        </world.quest.GDXQuest>
        <world.quest.GDXQuest>
          <name>fallout1</name>
          <prerequisites></prerequisites>
          <repeatable>false</repeatable>
          <trigger class="plugin.quest.trigger.aabb.AABBTrigger">
            <lowerLeft>
              <x>311.97342</x>
              <y>-31.50473</y>
            </lowerLeft>
            <upperRight>
              <x>312.94574</x>
              <y>-27.226522</y>
            </upperRight>
          </trigger>
          <manifestation class="plugin.quest.manifestation.physics.PhysicsManifestation">
            <name>fallout1</name>
            <impulse>
              <x>0.0</x>
              <y>0.0</y>
            </impulse>
            <type>DynamicBody</type>
            <torque>0.0</torque>
          </manifestation>
        </world.quest.GDXQuest>
        <world.quest.GDXQuest>
          <name>fallout2</name>
          <prerequisites></prerequisites>
          <repeatable>false</repeatable>
          <trigger class="plugin.quest.trigger.aabb.AABBTrigger">
            <lowerLeft>
              <x>316.46768</x>
              <y>-31.867731</y>
            </lowerLeft>
            <upperRight>
              <x>317.1375</x>
              <y>-26.21531</y>
            </upperRight>
          </trigger>
          <manifestation class="plugin.quest.manifestation.physics.PhysicsManifestation">
            <name>fallout2</name>
            <impulse>
              <x>0.0</x>
              <y>0.0</y>
            </impulse>
            <type>DynamicBody</type>
            <torque>0.0</torque>
          </manifestation>
        </world.quest.GDXQuest>
        <world.quest.GDXQuest>
          <name>fallout3</name>
          <prerequisites></prerequisites>
          <repeatable>false</repeatable>
          <trigger class="plugin.quest.trigger.aabb.AABBTrigger">
            <lowerLeft>
              <x>321.43732</x>
              <y>-31.660301</y>
            </lowerLeft>
            <upperRight>
              <x>321.9991</x>
              <y>-26.137524</y>
            </upperRight>
          </trigger>
          <manifestation class="plugin.quest.manifestation.physics.PhysicsManifestation">
            <name>fallout3</name>
            <impulse>
              <x>0.0</x>
              <y>0.0</y>
            </impulse>
            <type>DynamicBody</type>
            <torque>0.0</torque>
          </manifestation>
        </world.quest.GDXQuest>
        <world.quest.GDXQuest>
          <name>Quest-323</name>
          <prerequisites></prerequisites>
          <repeatable>false</repeatable>
          <trigger class="plugin.quest.trigger.activate.ActivateTrigger"/>
          <manifestation class="com.blastedstudios.velocitystack.quest.moneybag.MoneyBagManifestation">
            <position>
              <x>333.1917</x>
              <y>-30.478899</y>
            </position>
            <amount>50</amount>
          </manifestation>
        </world.quest.GDXQuest>
        <world.quest.GDXQuest>
          <name>Quest-324</name>
          <prerequisites></prerequisites>
          <repeatable>false</repeatable>
          <trigger class="plugin.quest.trigger.activate.ActivateTrigger"/>
          <manifestation class="com.blastedstudios.velocitystack.quest.moneybag.MoneyBagManifestation">
            <position>
              <x>338.2574</x>
              <y>-30.561417</y>
            </position>
            <amount>50</amount>
          </manifestation>
        </world.quest.GDXQuest>
        <world.quest.GDXQuest>
          <name>Quest-325</name>
          <prerequisites></prerequisites>
          <repeatable>false</repeatable>
          <trigger class="plugin.quest.trigger.activate.ActivateTrigger"/>
          <manifestation class="com.blastedstudios.velocitystack.quest.moneybag.MoneyBagManifestation">
            <position>
              <x>341.28302</x>
              <y>-30.726452</y>
            </position>
            <amount>50</amount>
          </manifestation>
        </world.quest.GDXQuest>
        <world.quest.GDXQuest>
          <name>platform2</name>
          <prerequisites></prerequisites>
          <repeatable>false</repeatable>
          <trigger class="plugin.quest.trigger.activate.ActivateTrigger"/>
          <manifestation class="plugin.quest.manifestation.platform.PlatformManifestation">
            <name>platform2</name>
            <joint>platform2Joint</joint>
            <pointA>
              <x>479.37946</x>
              <y>-37.0</y>
            </pointA>
            <pointB>
              <x>479.24832</x>
              <y>12.547535</y>
            </pointB>
            <waitDuration>5000</waitDuration>
            <maxMotorForceA>999.0</maxMotorForceA>
            <motorSpeedA>-5.0</motorSpeedA>
            <maxMotorForceB>999.0</maxMotorForceB>
            <motorSpeedB>5.0</motorSpeedB>
          </manifestation>
        </world.quest.GDXQuest>
        <world.quest.GDXQuest>
          <name>Quest-537</name>
          <prerequisites></prerequisites>
          <repeatable>false</repeatable>
          <trigger class="plugin.quest.trigger.activate.ActivateTrigger"/>
          <manifestation class="com.blastedstudios.velocitystack.quest.moneybag.MoneyBagManifestation">
            <position>
              <x>601.32135</x>
              <y>-9.989874</y>
            </position>
            <amount>100</amount>
          </manifestation>
        </world.quest.GDXQuest>
        <world.quest.GDXQuest>
          <name>Quest-538</name>
          <prerequisites></prerequisites>
          <repeatable>false</repeatable>
          <trigger class="plugin.quest.trigger.activate.ActivateTrigger"/>
          <manifestation class="com.blastedstudios.velocitystack.quest.moneybag.MoneyBagManifestation">
            <position>
              <x>607.2443</x>
              <y>-20.91647</y>
            </position>
            <amount>100</amount>
          </manifestation>
        </world.quest.GDXQuest>
        <world.quest.GDXQuest>
          <name>Quest-539</name>
          <prerequisites></prerequisites>
          <repeatable>false</repeatable>
          <trigger class="plugin.quest.trigger.activate.ActivateTrigger"/>
          <manifestation class="com.blastedstudios.velocitystack.quest.moneybag.MoneyBagManifestation">
            <position>
              <x>611.78046</x>
              <y>-32.373486</y>
            </position>
            <amount>100</amount>
          </manifestation>
        </world.quest.GDXQuest>
        <world.quest.GDXQuest>
          <name>Quest-588</name>
          <prerequisites></prerequisites>
          <repeatable>false</repeatable>
          <trigger class="plugin.quest.trigger.activate.ActivateTrigger"/>
          <manifestation class="com.blastedstudios.velocitystack.quest.moneybag.MoneyBagManifestation">
            <position>
              <x>649.9253</x>
              <y>-40.086002</y>
            </position>
            <amount>75</amount>
          </manifestation>
        </world.quest.GDXQuest>
        <world.quest.GDXQuest>
          <name>Quest-589</name>
          <prerequisites></prerequisites>
          <repeatable>false</repeatable>
          <trigger class="plugin.quest.trigger.activate.ActivateTrigger"/>
          <manifestation class="com.blastedstudios.velocitystack.quest.moneybag.MoneyBagManifestation">
            <position>
              <x>658.2234</x>
              <y>-44.15961</y>
            </position>
            <amount>75</amount>
          </manifestation>
        </world.quest.GDXQuest>
        <world.quest.GDXQuest>
          <name>Quest-590</name>
          <prerequisites></prerequisites>
          <repeatable>false</repeatable>
          <trigger class="plugin.quest.trigger.activate.ActivateTrigger"/>
          <manifestation class="com.blastedstudios.velocitystack.quest.moneybag.MoneyBagManifestation">
            <position>
              <x>666.5215</x>
              <y>-53.438374</y>
            </position>
            <amount>75</amount>
          </manifestation>
        </world.quest.GDXQuest>
        <world.quest.GDXQuest>
          <name>Quest-618</name>
          <prerequisites></prerequisites>
          <repeatable>false</repeatable>
          <trigger class="plugin.quest.trigger.activate.ActivateTrigger"/>
          <manifestation class="com.blastedstudios.velocitystack.quest.moneybag.MoneyBagManifestation">
            <position>
              <x>689.56384</x>
              <y>-71.45287</y>
            </position>
            <amount>50</amount>
          </manifestation>
        </world.quest.GDXQuest>
        <world.quest.GDXQuest>
          <name>Quest-619</name>
          <prerequisites></prerequisites>
          <repeatable>false</repeatable>
          <trigger class="plugin.quest.trigger.activate.ActivateTrigger"/>
          <manifestation class="com.blastedstudios.velocitystack.quest.moneybag.MoneyBagManifestation">
            <position>
              <x>690.94824</x>
              <y>-69.50518</y>
            </position>
            <amount>50</amount>
          </manifestation>
        </world.quest.GDXQuest>
        <world.quest.GDXQuest>
          <name>Quest-620</name>
          <prerequisites></prerequisites>
          <repeatable>false</repeatable>
          <trigger class="plugin.quest.trigger.activate.ActivateTrigger"/>
          <manifestation class="com.blastedstudios.velocitystack.quest.moneybag.MoneyBagManifestation">
            <position>
              <x>693.1203</x>
              <y>-72.02573</y>
            </position>
            <amount>50</amount>
          </manifestation>
        </world.quest.GDXQuest>
        <world.quest.GDXQuest>
          <name>endLevel</name>
          <prerequisites></prerequisites>
          <repeatable>false</repeatable>
          <trigger class="plugin.quest.trigger.aabb.AABBTrigger">
            <lowerLeft>
              <x>730.676</x>
              <y>-84.798035</y>
            </lowerLeft>
            <upperRight>
              <x>759.1409</x>
              <y>-43.51885</y>
            </upperRight>
          </trigger>
          <manifestation class="plugin.quest.manifestation.endlevel.EndLevelManifestation">
            <success>true</success>
          </manifestation>
        </world.quest.GDXQuest>
      </quests>
      <backgrounds>
        <world.GDXBackground>
          <coordinates>
            <x>0.0</x>
            <y>0.0</y>
          </coordinates>
          <texture>sky.png</texture>
          <scissor>false</scissor>
          <scissorPosition>
            <x>0.0</x>
            <y>0.0</y>
          </scissorPosition>
          <scissorDimensions>
            <x>0.0</x>
            <y>0.0</y>
          </scissorDimensions>
          <depth>100.0</depth>
          <scale>0.08</scale>
        </world.GDXBackground>
      </backgrounds>
      <lights/>
      <groups/>
      <particles/>
      <sounds/>
      <properties/>
      <lightAmbient>0</lightAmbient>
    </world.GDXLevel>
    <world.GDXLevel>
      <name>Vertical</name>
      <coordinates>
        <x>0.1999979</x>
        <y>-2.7999995</y>
      </coordinates>
      <tiles/>
      <circles/>
      <polygons>
        <world.shape.GDXPolygon>
          <name>Polygon-0</name>
          <resource>forest1.png</resource>
          <density>1.0</density>
          <friction>0.5</friction>
          <restitution>0.3</restitution>
          <bodyType>StaticBody</bodyType>
          <center>
            <x>29.328129</x>
            <y>-51.848583</y>
          </center>
          <repeatable>true</repeatable>
          <vertices>
            <Vector2>
              <x>-30.9135</x>
              <y>50.69039</y>
            </Vector2>
            <Vector2>
              <x>-29.553127</x>
              <y>50.66733</y>
            </Vector2>
            <Vector2>
              <x>-28.709377</x>
              <y>50.329834</y>
            </Vector2>
            <Vector2>
              <x>-27.668753</x>
              <y>49.418583</y>
            </Vector2>
            <Vector2>
              <x>-27.106253</x>
              <y>48.33858</y>
            </Vector2>
            <Vector2>
              <x>-17.47814</x>
              <y>-1.7754364</y>
            </Vector2>
            <Vector2>
              <x>-14.522346</x>
              <y>-11.533096</y>
            </Vector2>
            <Vector2>
              <x>-10.499033</x>
              <y>-13.303356</y>
            </Vector2>
            <Vector2>
              <x>-3.2570724</x>
              <y>-16.682934</y>
            </Vector2>
            <Vector2>
              <x>1.5709057</x>
              <y>-17.487598</y>
            </Vector2>
            <Vector2>
              <x>6.130665</x>
              <y>-18.292263</y>
            </Vector2>
            <Vector2>
              <x>11.495083</x>
              <y>-19.257862</y>
            </Vector2>
            <Vector2>
              <x>16.188946</x>
              <y>-19.579716</y>
            </Vector2>
            <Vector2>
              <x>19.273487</x>
              <y>-19.418789</y>
            </Vector2>
            <Vector2>
              <x>22.089802</x>
              <y>-18.775059</y>
            </Vector2>
            <Vector2>
              <x>23.96735</x>
              <y>-16.522007</y>
            </Vector2>
            <Vector2>
              <x>25.442562</x>
              <y>-12.015892</y>
            </Vector2>
            <Vector2>
              <x>26.381336</x>
              <y>-7.026985</y>
            </Vector2>
            <Vector2>
              <x>27.722454</x>
              <y>0.21498108</y>
            </Vector2>
            <Vector2>
              <x>42.34048</x>
              <y>-30.844997</y>
            </Vector2>
            <Vector2>
              <x>-32.895473</x>
              <y>-27.143543</y>
            </Vector2>
          </vertices>
        </world.shape.GDXPolygon>
      </polygons>
      <npcs/>
      <paths/>
      <joints/>
      <quests/>
      <backgrounds/>
      <lights/>
      <groups/>
      <particles/>
      <sounds/>
      <properties class="tree-map"/>
      <lightAmbient>-437918337</lightAmbient>
    </world.GDXLevel>
  </levels>
  <worldProperties>
    <entry>
      <string>background</string>
      <string></string>
    </entry>
  </worldProperties>
</world.GDXWorld>